dictfilter/__init__.py
dictfilter/core.py
dictfilter/version.py
dictfilter/django/__init__.py
dictfilter/django/middleware.py
tests/__init__.py
tests/test_django.py
tests/test_query.py
dictfilter-2.1.dist-info/LICENSE
dictfilter-2.1.dist-info/METADATA
dictfilter-2.1.dist-info/WHEEL
dictfilter-2.1.dist-info/top_level.txt
dictfilter-2.1.dist-info/RECORD
