Metadata-Version: 2.1
Name: dictfilter
Version: 2.1
Summary: Filter dictionaries based on a list of field names.
Home-page: https://github.com/binkhq/dictfilter
Author: Chris Latham
Author-email: opensource@bink.com
License: MIT
Platform: UNKNOWN
Classifier: Programming Language :: Python :: 3
Classifier: License :: OSI Approved :: MIT License
Classifier: Operating System :: OS Independent
License-File: LICENSE
